Metadata-Version: 2.1
Name: faststream-gen
Version: 0.1.7
Summary: The faststream-gen library uses advanced AI to generate FastStream code from user descriptions, speeding up FastStream app development.
Home-page: https://github.com/airtai/faststream-gen
Author: airt
Author-email: info@airt.ai
License: Apache Software License 2.0
Keywords: nbdev jupyter notebook python
Platform: UNKNOWN
Classifier: Development Status :: 4 - Beta
Classifier: Intended Audience :: Developers
Classifier: Natural Language :: English
Classifier: Programming Language :: Python :: 3.8
Classifier: Programming Language :: Python :: 3.9
Classifier: Programming Language :: Python :: 3.10
Classifier: Programming Language :: Python :: 3.11
Classifier: License :: OSI Approved :: Apache Software License
Requires-Python: >=3.8
License-File: LICENSE
Requires-Dist: asyncio (==3.4.3)
Requires-Dist: faiss-cpu (>=1.7.4)
Requires-Dist: fastcore (==1.5.29)
Requires-Dist: faststream[kafka,rabbit,testing] (>=0.1.5)
Requires-Dist: langchain (>=0.0.276)
Requires-Dist: openai (>=0.27.8)
Requires-Dist: tiktoken (>=0.4.0)
Requires-Dist: toml (==0.10.2)
Requires-Dist: typer (>=0.9.0)
Requires-Dist: unstructured (==0.10.10)
Requires-Dist: yaspin (>=2.3.0)
Provides-Extra: dev
Requires-Dist: bandit (==1.7.5) ; extra == 'dev'
Requires-Dist: black (==23.7.0) ; extra == 'dev'
Requires-Dist: detect-secrets (==1.4.0) ; extra == 'dev'
Requires-Dist: isort (==5.12.0) ; extra == 'dev'
Requires-Dist: mypy (==1.5.1) ; extra == 'dev'
Requires-Dist: nbdev-mkdocs (==0.6.0) ; extra == 'dev'
Requires-Dist: nbqa (==1.7.0) ; extra == 'dev'
Requires-Dist: pre-commit (==3.3.3) ; extra == 'dev'
Requires-Dist: pytest (==7.4.2) ; extra == 'dev'
Requires-Dist: semgrep (==1.34.1) ; extra == 'dev'
